[
	{
		"productId": "573A88E7-C9E4-479D-BCB6-159B60596F88",
		"name": "ПЕРЧАТКИ ЗАМША ",
		"price": 2400,
		"desc": "",
		"opt_price": 2400,
		"vendor": "2400ZM",
		"barcode": "2621000170265",
		"active": true,
		"categoryId": "A009671C-11F2-49B3-9A43-2CD8479A7AFA",
		"sizeId": "",
		"sizeName": ""
	},
	{
		"productId": "8C083EEF-E729-4174-92B2-EFBB836B8847",
		"name": "ПЕРЧАТКИ ЗАМША",
		"price": 2800,
		"desc": "",
		"opt_price": 2800,
		"vendor": "2800ZM",
		"barcode": "2680000170255",
		"active": true,
		"categoryId": "DBCC510F-D141-4E2B-B128-00726B710F9E",
		"sizeId": "",
		"sizeName": ""
	},
	{
		"productId": "3023CEEB-EF40-480D-9358-3C43F8CD3327",
		"name": "ПЕРЧАТКИ КОЖА",
		"price": 3100,
		"desc": "",
		"opt_price": 3100,
		"vendor": "3100KZ",
		"barcode": "2631000082710",
		"active": true,
		"categoryId": "DBCC510F-D141-4E2B-B128-00726B710F9E",
		"sizeId": "",
		"sizeName": ""
	},
	{
		"productId": "760B5D1F-D487-4A37-9DC0-12F097DB8C4B",
		"name": "ПЕРЧАТКИ APAILONG",
		"price": 5400,
		"desc": "",
		"opt_price": 5400,
		"vendor": "APLNG2632",
		"barcode": "2620000073873",
		"active": true,
		"categoryId": "A009671C-11F2-49B3-9A43-2CD8479A7AFA",
		"sizeId": "",
		"sizeName": ""
	},
	{
		"productId": "D1689FD1-AED9-4966-9A0B-F492A7FFFBBC",
		"name": "КОРОБКА BELT",
		"price": 200,
		"desc": "",
		"opt_price": 200,
		"vendor": "BELT1",
		"barcode": "2635000060136",
		"active": true,
		"categoryId": "DBCC510F-D141-4E2B-B128-00726B710F9E",
		"sizeId": "",
		"sizeName": ""
	},
	{
		"productId": "36A59655-FCDC-469E-AFD2-EABC30776D2E",
		"name": "КОРОБКА CASIO",
		"price": 1500,
		"desc": "",
		"opt_price": 1500,
		"vendor": "CASIO/BOX1,8",
		"barcode": "2628000014957",
		"active": true,
		"categoryId": "DBCC510F-D141-4E2B-B128-00726B710F9E",
		"sizeId": "",
		"sizeName": ""
	},
	{
		"productId": "D028D411-57CC-4203-BFF6-3C429730011E",
		"name": "ПАКЕТ",
		"price": 100,
		"desc": "",
		"opt_price": 100,
		"vendor": "PAKET100",
		"barcode": "2649000165531",
		"active": true,
		"categoryId": "A009671C-11F2-49B3-9A43-2CD8479A7AFA",
		"sizeId": "",
		"sizeName": ""
	},
	{
		"productId": "B9577072-E716-4AE8-BC20-25DDCAAD5371",
		"name": "ВЕШАЛКИ ПРИЩЕПКА",
		"price": 100,
		"desc": "",
		"opt_price": 100,
		"vendor": "VESHALKI50",
		"barcode": "2617000143538",
		"active": true,
		"categoryId": "E1EBC5FD-9DFD-4C36-AA56-C6F3128B3969",
		"sizeId": "",
		"sizeName": ""
	},
	{
		"productId": "B1DF5E04-6956-409C-87BC-D93D65BBE1B6",
		"name": "ВЕШАЛКИ ПЛЕЧИКИ",
		"price": 5000,
		"desc": "",
		"opt_price": 5000,
		"vendor": "VESHALKI500",
		"barcode": "2610000143522",
		"active": true,
		"categoryId": "E1EBC5FD-9DFD-4C36-AA56-C6F3128B3969",
		"sizeId": "",
		"sizeName": ""
	},
	{
		"productId": "31D548B0-4578-4FAE-B2DA-4E180248DC30",
		"name": "ZONT ",
		"price": 12000,
		"desc": "",
		"opt_price": 12000,
		"vendor": "ZONT12000",
		"barcode": "2691000014203",
		"active": true,
		"categoryId": "E1EBC5FD-9DFD-4C36-AA56-C6F3128B3969",
		"sizeId": "",
		"sizeName": ""
	},
	{
		"productId": "2C698B68-B8A0-4F8A-9429-BC021C05E411",
		"name": "Зонт",
		"price": 3000,
		"desc": "",
		"opt_price": 3000,
		"vendor": "ZONT3000",
		"barcode": "2697000037174",
		"active": true,
		"categoryId": "E1EBC5FD-9DFD-4C36-AA56-C6F3128B3969",
		"sizeId": "",
		"sizeName": ""
	}
]
